nonebot_plugin_argot/__init__.py
nonebot_plugin_argot/data_source.py
nonebot_plugin_argot/event.py
nonebot_plugin_argot/extension.py
nonebot_plugin_argot/hook.py
nonebot_plugin_argot/matcher.py
nonebot_plugin_argot/message.py
nonebot_plugin_argot/segment.py
nonebot_plugin_argot/typing.py
nonebot_plugin_argot/utils.py
nonebot_plugin_argot-0.2.2.dist-info/licenses/LICENSE
nonebot_plugin_argot-0.2.2.dist-info/METADATA
nonebot_plugin_argot-0.2.2.dist-info/WHEEL
nonebot_plugin_argot-0.2.2.dist-info/top_level.txt
nonebot_plugin_argot-0.2.2.dist-info/RECORD
