Metadata-Version: 2.4
Name: nonebot-plugin-argot
Version: 0.2.2
Summary: NoneBot 暗语
Author-email: KomoriDev <mute231010@gmail.com>
License: MIT
Requires-Python: >=3.10
License-File: LICENSE
Requires-Dist: nonebot2>=2.3.2
Requires-Dist: nonebot-plugin-alconna>=0.58.2
Requires-Dist: nonebot-plugin-apscheduler>=0.5.0
Requires-Dist: nonebot-plugin-localstore>=0.7.4
Requires-Dist: aiofiles>=24.1.0
Requires-Dist: arclet-letoderea>=0.17.0
Provides-Extra: tests
Requires-Dist: nonebug>=0.3.7; extra == "tests"
Requires-Dist: pytest-mock>=3.14.0; extra == "tests"
Requires-Dist: pytest-asyncio>=0.23.8; extra == "tests"
Dynamic: license-file
